CHANGELOG.md
pydantic_factories/__init__.py
pydantic_factories/constraints/__init__.py
pydantic_factories/constraints/collection.py
pydantic_factories/constraints/date.py
pydantic_factories/constraints/decimal.py
pydantic_factories/constraints/float.py
pydantic_factories/constraints/integer.py
pydantic_factories/constraints/strings.py
pydantic_factories/exceptions.py
pydantic_factories/extensions/__init__.py
pydantic_factories/extensions/beanie_odm.py
pydantic_factories/extensions/odmantic_odm.py
pydantic_factories/extensions/ormar_orm.py
pydantic_factories/factory.py
pydantic_factories/fields.py
pydantic_factories/plugins/__init__.py
pydantic_factories/plugins/pytest_plugin.py
pydantic_factories/protocols.py
pydantic_factories/py.typed
pydantic_factories/utils.py
pydantic_factories/value_generators/__init__.py
pydantic_factories/value_generators/complex_types.py
pydantic_factories/value_generators/constrained_number.py
pydantic_factories/value_generators/primitives.py
pydantic_factories/value_generators/regex.py
pydantic_factories-1.17.3.dist-info/LICENSE
pydantic_factories-1.17.3.dist-info/METADATA
pydantic_factories-1.17.3.dist-info/WHEEL
pydantic_factories-1.17.3.dist-info/RECORD
