Metadata-Version: 2.1
Name: pydantic-factories
Version: 1.17.3
Summary: Mock data generation for pydantic based models and python dataclasses
Home-page: https://github.com/starlite-api/pydantic-factories
License: MIT
Keywords: dataclasses,factory,faker,mock,pydantic,pytest,starlite,tdd,testing
Author: Na'aman Hirschfeld
Author-email: nhirschfeld@gmail.com
Maintainer: Na'aman Hirschfeld
Maintainer-email: nhirschfeld@gmail.com
Requires-Python: >=3.8,<4.0
Classifier: Environment :: Web Environment
Classifier: Framework :: Pytest
Classifier: Intended Audience :: Developers
Classifier: License :: OSI Approved :: MIT License
Classifier: Natural Language :: English
Classifier: Operating System :: OS Independent
Classifier: Programming Language :: Python
Classifier: Programming Language :: Python :: 3
Classifier: Programming Language :: Python :: 3.8
Classifier: Programming Language :: Python :: 3.9
Classifier: Programming Language :: Python :: 3.10
Classifier: Programming Language :: Python :: 3.11
Classifier: Programming Language :: Python :: 3.10
Classifier: Programming Language :: Python :: 3.11
Classifier: Programming Language :: Python :: 3.8
Classifier: Programming Language :: Python :: 3.9
Classifier: Topic :: Software Development
Classifier: Topic :: Software Development :: Libraries
Classifier: Topic :: Software Development :: Testing
Classifier: Topic :: Software Development :: Testing :: Unit
Classifier: Topic :: Utilities
Classifier: Typing :: Typed
Requires-Dist: faker
Requires-Dist: pydantic (>=1.10.0)
Requires-Dist: typing-extensions
Project-URL: Documentation, https://github.com/starlite-api/pydantic-factories
Project-URL: Repository, https://github.com/starlite-api/pydantic-factories
